pip_services4_container/__init__.py
pip_services4_container/build/DefaultContainerFactory.py
pip_services4_container/build/__init__.py
pip_services4_container/config/ComponentConfig.py
pip_services4_container/config/ContainerConfig.py
pip_services4_container/config/ContainerConfigReader.py
pip_services4_container/config/__init__.py
pip_services4_container/container/Container.py
pip_services4_container/container/ProcessContainer.py
pip_services4_container/container/__init__.py
pip_services4_container/refer/BuildReferencesDecorator.py
pip_services4_container/refer/ContainerReferences.py
pip_services4_container/refer/LinkReferencesDecorator.py
pip_services4_container/refer/ManagedReferences.py
pip_services4_container/refer/ReferencesDecorator.py
pip_services4_container/refer/RunReferencesDecorator.py
pip_services4_container/refer/__init__.py
pip_services4_container/test/DefaultTestFactory.py
pip_services4_container/test/SetInterval.py
pip_services4_container/test/Shutdown.py
pip_services4_container/test/__init__.py
pip_services4_container-0.0.1.dist-info/LICENSE
pip_services4_container-0.0.1.dist-info/METADATA
pip_services4_container-0.0.1.dist-info/WHEEL
pip_services4_container-0.0.1.dist-info/top_level.txt
pip_services4_container-0.0.1.dist-info/zip-safe
pip_services4_container-0.0.1.dist-info/RECORD
