Metadata-Version: 2.1
Name: pip-services4-container
Version: 0.0.1
Summary: IoC container for Pip.Services in Python
Home-page: http://github.com/pip-services3-python/pip-services4-container-python
Author: Conceptual Vision Consulting LLC
Author-email: seroukhov@gmail.com
License: MIT
Platform: any
Classifier: Development Status :: 4 - Beta
Classifier: Intended Audience :: Developers
Classifier: License :: OSI Approved :: MIT License
Classifier: Operating System :: OS Independent
Classifier: Programming Language :: Python
Classifier: Programming Language :: Python :: 3.6
Classifier: Programming Language :: Python :: 3.7
Classifier: Programming Language :: Python :: 3.8
Classifier: Topic :: Software Development :: Libraries :: Python Modules
License-File: LICENSE
Requires-Dist: pytest
Requires-Dist: pip-services4-commons <1.0,>=0.0.1
Requires-Dist: pip-services4-components <1.0,>=0.0.8
Requires-Dist: pip-services4-config <1.0,>=0.0.2
Requires-Dist: pip-services4-logic <1.0,>=0.0.5
Requires-Dist: pip-services4-observability <1.0,>=0.0.2
